LICENSE
MANIFEST.in
README.md
VERSION
requirements.txt
setup.cfg
setup.py
Non_Blocking_Http_Logging_Handler.egg-info/PKG-INFO
Non_Blocking_Http_Logging_Handler.egg-info/SOURCES.txt
Non_Blocking_Http_Logging_Handler.egg-info/dependency_links.txt
Non_Blocking_Http_Logging_Handler.egg-info/top_level.txt
Non_Blocking_Http_Logging_Handler.egg-info/zip-safe
examples/__init__.py
examples/basic_usage.py
examples/extra_fields.py
non_blocking_http_handler/__init__.py
non_blocking_http_handler/handler.py