Metadata-Version: 2.1
Name: Non-Blocking-Http-Logging-Handler
Version: 1.0.3
Summary: Python logging handler that sends log records to a HTTP server in a non-blocking way.
Home-page: https://github.com/whoami-jc/non-blocking-http-logging-handler
Author: Juan Carlos
Author-email: whoami0jc@gmail.com
License: License :: OSI Approved :: MIT License
Platform: UNKNOWN
Classifier: License :: OSI Approved :: MIT License
Classifier: Programming Language :: Python :: 3.8
Classifier: Programming Language :: Python :: 3.9
Classifier: Programming Language :: Python :: 3.10
Classifier: Programming Language :: Python :: 3.11
Classifier: Environment :: Console
Classifier: Operating System :: POSIX
Classifier: Operating System :: MacOS
Classifier: Operating System :: OS Independent
Classifier: Operating System :: Microsoft :: Windows
